schuylkill/__init__.py
schuylkill/exact.py
schuylkill/fuzzy.py
schuylkill/tests/__init__.py
schuylkill/tests/test_exact.py
schuylkill/tests/test_fuzzy.py
schuylkill/tests/test_utils.py
schuylkill/tf_idf.py
schuylkill/utils.py
schuylkill-0.1.2.dist-info/LICENSE
schuylkill-0.1.2.dist-info/WHEEL
schuylkill-0.1.2.dist-info/METADATA
schuylkill-0.1.2.dist-info/RECORD
